medrs-0.1.2.dist-info/METADATA
medrs-0.1.2.dist-info/WHEEL
medrs-0.1.2.dist-info/licenses/LICENSE
medrs/__init__.py
medrs/_medrs.cpython-312-darwin.so
medrs/_medrs.pyi
medrs/dictionary_transforms.py
medrs/exceptions.py
medrs/metatensor_support.py
medrs/monai_compat.py
medrs/performance_profiler.py
medrs-0.1.2.dist-info/RECORD
