Metadata-Version: 2.4
Name: medrs
Version: 0.1.2
Classifier: Development Status :: 3 - Alpha
Classifier: Intended Audience :: Science/Research
Classifier: Intended Audience :: Healthcare Industry
Classifier: License :: OSI Approved :: MIT License
Classifier: License :: OSI Approved :: Apache Software License
Classifier: Programming Language :: Python :: 3
Classifier: Programming Language :: Python :: 3.10
Classifier: Programming Language :: Python :: 3.11
Classifier: Programming Language :: Python :: 3.12
Classifier: Programming Language :: Python :: 3.13
Classifier: Programming Language :: Rust
Classifier: Topic :: Scientific/Engineering :: Medical Science Apps.
Classifier: Topic :: Scientific/Engineering :: Image Processing
Requires-Dist: numpy>=1.25.0
Requires-Dist: pytest>=7.0 ; extra == 'dev'
Requires-Dist: pytest-benchmark>=4.0 ; extra == 'dev'
Requires-Dist: psutil>=5.9 ; extra == 'dev'
Requires-Dist: nibabel>=5.0 ; extra == 'dev'
Requires-Dist: torch>=2.0 ; extra == 'dev'
Requires-Dist: monai>=1.5 ; extra == 'dev'
Requires-Dist: jax>=0.4 ; extra == 'dev'
Requires-Dist: jaxlib>=0.4 ; extra == 'dev'
Requires-Dist: hypothesis>=6.0 ; extra == 'dev'
Requires-Dist: monai>=1.5 ; extra == 'monai'
Requires-Dist: torch>=2.0 ; extra == 'monai'
Requires-Dist: nibabel>=5.0 ; extra == 'monai'
Requires-Dist: jax>=0.4 ; extra == 'jax'
Requires-Dist: jaxlib>=0.4 ; extra == 'jax'
Requires-Dist: torch>=2.0 ; extra == 'torch'
Requires-Dist: torch>=2.0 ; extra == 'examples'
Requires-Dist: monai>=1.5 ; extra == 'examples'
Requires-Dist: nibabel>=5.0 ; extra == 'examples'
Requires-Dist: jax>=0.4 ; extra == 'examples'
Requires-Dist: torchio>=0.20 ; extra == 'examples'
Requires-Dist: matplotlib>=3.5 ; extra == 'examples'
Requires-Dist: sphinx>=7.0 ; extra == 'docs'
Requires-Dist: sphinx-rtd-theme>=1.3 ; extra == 'docs'
Requires-Dist: sphinx-tabs>=3.4 ; extra == 'docs'
Requires-Dist: sphinx-copybutton>=0.5 ; extra == 'docs'
Requires-Dist: sphinx-design>=0.5 ; extra == 'docs'
Requires-Dist: myst-parser>=2.0 ; extra == 'docs'
Requires-Dist: sphinx-autodoc-typehints>=1.24 ; extra == 'docs'
Requires-Dist: numpy>=1.25.0 ; extra == 'docs'
Requires-Dist: pytest>=7.0 ; extra == 'test'
Requires-Dist: pytest-benchmark>=4.0 ; extra == 'test'
Requires-Dist: pytest-xdist>=3.0 ; extra == 'test'
Requires-Dist: psutil>=5.9 ; extra == 'test'
Requires-Dist: nibabel>=5.0 ; extra == 'test'
Requires-Dist: hypothesis>=6.0 ; extra == 'test'
Provides-Extra: dev
Provides-Extra: monai
Provides-Extra: jax
Provides-Extra: torch
Provides-Extra: examples
Provides-Extra: docs
Provides-Extra: test
License-File: LICENSE
Summary: Ultra-high-performance medical imaging I/O for deep learning
Keywords: medical-imaging,nifti,neuroimaging,deep-learning,pytorch,jax,monai
Home-Page: https://github.com/liamchalcroft/med-rs
Author-email: Liam Chalcroft <liam.chalcroft.20@ucl.ac.uk>
Maintainer-email: Liam Chalcroft <liam.chalcroft.20@ucl.ac.uk>
License: MIT OR Apache-2.0
Requires-Python: >=3.10
Project-URL: Homepage, https://github.com/liamchalcroft/med-rs
Project-URL: Documentation, https://medrs.readthedocs.io
Project-URL: Repository, https://github.com/liamchalcroft/med-rs
Project-URL: Bug Tracker, https://github.com/liamchalcroft/med-rs/issues
